jeedomdaemon/__init__.py
jeedomdaemon/aio_connector.py
jeedomdaemon/base_config.py
jeedomdaemon/base_daemon.py
jeedomdaemon/utils.py
jeedomdaemon/version.py
jeedomdaemon-1.2.6.dist-info/LICENSE
jeedomdaemon-1.2.6.dist-info/METADATA
jeedomdaemon-1.2.6.dist-info/WHEEL
jeedomdaemon-1.2.6.dist-info/top_level.txt
jeedomdaemon-1.2.6.dist-info/RECORD
