Metadata-Version: 2.2
Name: jeedomdaemon
Version: 1.2.6
Summary: A base to implement Jeedom daemon in python
Author: Mips
Project-URL: Homepage, https://github.com/Mips2648/jeedom-daemon-py
Keywords: JEEDOM,DAEMON,ASYNCIO
Classifier: Development Status :: 5 - Production/Stable
Classifier: Intended Audience :: Developers
Classifier: Topic :: Software Development :: Build Tools
Classifier: Programming Language :: Python :: 3
Classifier: Programming Language :: Python :: 3.9
Classifier: Programming Language :: Python :: 3.11
Requires-Python: >=3.9
License-File: LICENSE
Requires-Dist: aiohttp
